Metadata-Version: 2.1
Name: django-easy-softdelete
Version: 0.1.0
Summary: Some users want a “recycling bin” or “archival” feature which allows
Home-page: https://github.com/mabukhashabeh/django-easy-softdelete
Author: Mohammad Abu Khashabeh
Author-email: abukhashabehmohammad@gmail.com
License: BSD
Keywords: django-easy-softdelete,delete,safedelete,softdelete,django
Platform: UNKNOWN
Classifier: Framework :: Django
Classifier: Intended Audience :: Developers
Classifier: License :: OSI Approved :: BSD License
Classifier: Programming Language :: Python
Classifier: Programming Language :: Python :: 2
Classifier: Programming Language :: Python :: 2.7
Classifier: Programming Language :: Python :: 3
Classifier: Programming Language :: Python :: 3.3
Classifier: Programming Language :: Python :: 3.4
Classifier: Programming Language :: Python :: 3.5
Classifier: Programming Language :: Python :: 3.6
Classifier: Programming Language :: Python :: 3.7
Classifier: Programming Language :: Python :: 3.8
Classifier: Development Status :: 4 - Beta
